assemblyline/__init__.py
assemblyline/cachestore/__init__.py
assemblyline/common/__init__.py
assemblyline/common/attack_map.py
assemblyline/common/auth_email.py
assemblyline/common/backupmanager.py
assemblyline/common/banner.py
assemblyline/common/bundling.py
assemblyline/common/caching.py
assemblyline/common/chunk.py
assemblyline/common/classification.py
assemblyline/common/classification.yml
assemblyline/common/codec.py
assemblyline/common/compat_tag_map.py
assemblyline/common/constants.py
assemblyline/common/context.py
assemblyline/common/custom.magic
assemblyline/common/dict_utils.py
assemblyline/common/digests.py
assemblyline/common/entropy.py
assemblyline/common/exceptions.py
assemblyline/common/forge.py
assemblyline/common/frequency.pyx
assemblyline/common/hexdump.py
assemblyline/common/identify.py
assemblyline/common/importing.py
assemblyline/common/iprange.py
assemblyline/common/isotime.py
assemblyline/common/log.py
assemblyline/common/logformat.py
assemblyline/common/memory_zip.py
assemblyline/common/metrics.py
assemblyline/common/net.py
assemblyline/common/net_static.py
assemblyline/common/null.py
assemblyline/common/path.py
assemblyline/common/security.py
assemblyline/common/signaturing.py
assemblyline/common/str_utils.py
assemblyline/common/tagging.py
assemblyline/common/testing.py
assemblyline/common/uid.py
assemblyline/common/version.py
assemblyline/datasource/__init__.py
assemblyline/datasource/al.py
assemblyline/datasource/alert.py
assemblyline/datasource/common.py
assemblyline/datastore/__init__.py
assemblyline/datastore/exceptions.py
assemblyline/datastore/helper.py
assemblyline/datastore/stores/__init__.py
assemblyline/datastore/stores/es_store.py
assemblyline/datastore/support/__init__.py
assemblyline/datastore/support/elasticsearch/__init__.py
assemblyline/datastore/support/elasticsearch/build.py
assemblyline/datastore/support/elasticsearch/schemas.py
assemblyline/filestore/__init__.py
assemblyline/filestore/transport/__init__.py
assemblyline-4.0.0.dev150.dist-info/LICENCE.md
assemblyline-4.0.0.dev150.dist-info/METADATA
assemblyline-4.0.0.dev150.dist-info/WHEEL
assemblyline-4.0.0.dev150.dist-info/top_level.txt
assemblyline-4.0.0.dev150.dist-info/RECORD
