Metadata-Version: 2.1
Name: assemblyline
Version: 4.0.0.dev150
Summary: Assemblyline (v4) automated malware analysis framework base package.
Home-page: https://bitbucket.org/cse-assemblyline/alv4/
Author: CCCS Assemblyline development team
Author-email: assemblyline@cyber.gc.ca
License: MIT
Keywords: assemblyline malware gc canada cse-cst cse cst cyber cccs
Platform: UNKNOWN
Classifier: Development Status :: 2 - Pre-Alpha
Classifier: Intended Audience :: Developers
Classifier: Topic :: Software Development :: Libraries
Classifier: License :: OSI Approved :: MIT License
Classifier: Programming Language :: Python :: 3.7
Classifier: Programming Language :: Python :: 3.8
Requires-Dist: arrow (==0.14.4)
Requires-Dist: urllib3 (<1.25)
Requires-Dist: python-baseconv
Requires-Dist: boto3
Requires-Dist: pysftp
Requires-Dist: netifaces
Requires-Dist: pyroute2
Requires-Dist: redis
Requires-Dist: requests
Requires-Dist: elasticsearch (!=7.0.3,<8.0.0,>=7.0.0)
Requires-Dist: python-datemath
Requires-Dist: packaging
Requires-Dist: tabulate
Requires-Dist: PyYAML
Requires-Dist: easydict
Requires-Dist: passlib
Requires-Dist: cart
Requires-Dist: ssdeep
Requires-Dist: python-magic
Requires-Dist: apscheduler
Requires-Dist: elastic-apm[flask]
Requires-Dist: cython
Requires-Dist: docker
Requires-Dist: kubernetes
Requires-Dist: notifications-python-client
